URAG/URAG.py
URAG/__init__.py
URAG-0.0.1.dist-info/LICENSE
URAG-0.0.1.dist-info/METADATA
URAG-0.0.1.dist-info/WHEEL
URAG-0.0.1.dist-info/top_level.txt
URAG-0.0.1.dist-info/RECORD
