Metadata-Version: 2.1
Name: URAG
Version: 0.0.1
Summary: Build your own chatbot in no time!
Home-page: https://github.com/masoud-n91/RAG
Author: Masoud Navidi
Author-email: navidi.m.91@gmail.com
Classifier: Programming Language :: Python :: 3
Classifier: License :: OSI Approved :: MIT License
Requires-Python: >=3.9
License-File: LICENSE
Requires-Dist: python-docx ==1.1.0
Requires-Dist: groq ==0.5.0
Requires-Dist: annoy ==1.17.3
Requires-Dist: sentence-transformers ==2.7.0
Requires-Dist: torch ==2.3.0
Requires-Dist: huggingface-hub ==0.17.3
Requires-Dist: numpy ==1.26.4
Requires-Dist: pillow ==10.3.0
Requires-Dist: scikit-learn ==1.4.2
Requires-Dist: transformers ==4.34.0
Requires-Dist: beautifulsoup4 ==4.12.3
